gradify/__init__.py
gradify/core.py
py_gradify-0.2.0.dist-info/METADATA
py_gradify-0.2.0.dist-info/WHEEL
py_gradify-0.2.0.dist-info/top_level.txt
py_gradify-0.2.0.dist-info/RECORD
